pyjeasy/__init__.py
pyjeasy/base/__init__.py
pyjeasy/base/base_classes.py
pyjeasy/check_utils/__init__.py
pyjeasy/check_utils/check.py
pyjeasy/data_utils/__init__.py
pyjeasy/data_utils/data.py
pyjeasy/file_utils/__init__.py
pyjeasy/file_utils/file_func.py
pyjeasy/file_utils/path.py
pyjeasy/file_utils/path_func.py
pyjeasy/image_utils/__init__.py
pyjeasy/image_utils/compare_images.py
pyjeasy/image_utils/concate.py
pyjeasy/image_utils/crop.py
pyjeasy/image_utils/mask_lib.py
pyjeasy/image_utils/preview.py
pyjeasy/image_utils/convert/__init__.py
pyjeasy/image_utils/convert/image_utils_convert_data.py
pyjeasy/image_utils/convert/images2video.py
pyjeasy/image_utils/convert/multiple_frame2one.py
pyjeasy/image_utils/convert/remove_audio.py
pyjeasy/image_utils/convert/video2images.py
pyjeasy/image_utils/draw/__init__.py
pyjeasy/image_utils/draw/drawing_utils.py
pyjeasy/image_utils/edit/__init__.py
pyjeasy/image_utils/edit/edit_image.py
pyjeasy/image_utils/edit/merge_colors.py
pyjeasy/math_utils/__init__.py
pyjeasy/math_utils/math_func.py
pyjeasy/structure/__init__.py
pyjeasy/structure/bbox.py
pyjeasy/structure/keypoint.py
pyjeasy/structure/point.py
pyjeasy/structure/segmentation.py
pyjeasy-0.1.1.dist-info/LICENSE
pyjeasy-0.1.1.dist-info/METADATA
pyjeasy-0.1.1.dist-info/WHEEL
pyjeasy-0.1.1.dist-info/top_level.txt
pyjeasy-0.1.1.dist-info/RECORD
