Metadata-Version: 2.1
Name: pyjeasy
Version: 0.1.1
Summary: Useful python tools
Home-page: https://github.com/Jitesh17/pyjeasy
Author: Jitesh Gosar
Author-email: gosar95@gmail.com
License: UNKNOWN
Platform: UNKNOWN
Classifier: Programming Language :: Python :: 3
Classifier: Programming Language :: Python :: 3.5
Classifier: Programming Language :: Python :: 3.6
Classifier: Programming Language :: Python :: 3.7
Classifier: License :: OSI Approved :: MIT License
Classifier: Operating System :: OS Independent
Requires-Python: >=3.6
Requires-Dist: printj
Requires-Dist: opencv-python
Requires-Dist: numpy
Requires-Dist: matplotlib
Requires-Dist: pandas
